MANIFEST.in
README.md
requirements.txt
setup.cfg
setup.py
imaxtml/__init__.py
imaxtml.egg-info/PKG-INFO
imaxtml.egg-info/SOURCES.txt
imaxtml.egg-info/dependency_links.txt
imaxtml.egg-info/not-zip-safe
imaxtml.egg-info/requires.txt
imaxtml.egg-info/top_level.txt
imaxtml/models/__init__.py
imaxtml/models/unet.py